tinydb_helper/__init__.py
tinydb_helper/helper.py
tinydb_helper-0.1.5.dist-info/LICENSE.txt
tinydb_helper-0.1.5.dist-info/METADATA
tinydb_helper-0.1.5.dist-info/WHEEL
tinydb_helper-0.1.5.dist-info/RECORD
