Metadata-Version: 2.1
Name: tinydb-helper
Version: 0.1.5
Summary: Tinydb CRUD wrapper for table
Home-page: https://github.com/jnguyen0220/tinydb-helper
Author: Jonny Nguyen
Author-email: jonny_nguyen@outlook.com
Requires-Python: >=3.9,<4.0
Classifier: Programming Language :: Python :: 3
Classifier: Programming Language :: Python :: 3.9
Classifier: Programming Language :: Python :: 3.10
Classifier: Programming Language :: Python :: 3.11
Classifier: Programming Language :: Python :: 3.12
Requires-Dist: pre-commit (>=3.8.0,<4.0.0)
Requires-Dist: tinydb (>=4.8.0,<5.0.0)
Project-URL: Documentation, https://github.com/jnguyen0220/tinydb-helper/blob/main/README.md
Project-URL: Repository, https://github.com/jnguyen0220/tinydb-helper
